sfftk_migrate/__init__.py
sfftk_migrate/core.py
sfftk_migrate/main.py
sfftk_migrate/migrate.py
sfftk_migrate/test_sfftk_migrate.py
sfftk_migrate/tests.py
sfftk_migrate/utils.py
sfftk_migrate/migrations/__init__.py
sfftk_migrate/migrations/migrate_v0_7_0_dev0_to_v0_8_0_dev1.py
sfftk_migrate/migrations/migrate_v1_to_v2.py
sfftk_migrate/stylesheets/identity.xsl
sfftk_migrate/stylesheets/migrate_v0.7.0.dev0_to_v0.8.0.dev0.xsl
sfftk_migrate/stylesheets/migrate_v0.7.0.dev0_to_v0.8.0.dev1.xsl
sfftk_migrate/stylesheets/migrate_v1_to_v2.xsl
sfftk_migrate-0.1.1.dist-info/LICENSE
sfftk_migrate-0.1.1.dist-info/METADATA
sfftk_migrate-0.1.1.dist-info/WHEEL
sfftk_migrate-0.1.1.dist-info/entry_points.txt
sfftk_migrate-0.1.1.dist-info/top_level.txt
sfftk_migrate-0.1.1.dist-info/RECORD
